LICENSE
MANIFEST.in
README.md
VERSION
setup.cfg
setup.py
supervisor_confator/__init__.py
supervisor_confator/tests.py
supervisor_confator.egg-info/PKG-INFO
supervisor_confator.egg-info/SOURCES.txt
supervisor_confator.egg-info/dependency_links.txt
supervisor_confator.egg-info/top_level.txt