Metadata-Version: 1.1
Name: supervisor-confator
Version: 0.3.0
Summary: Python interface to generate supervisor configuration files.
Home-page: https://github.com/alexhayes/supervisor-confator
Author: Alex Hayes
Author-email: alex@alution.com
License: MIT
Download-URL: https://github.com/alexhayes/supervisor-confator/tarball/0.3.0
Keywords: supervisor,config,generator,server management
Platform: UNKNOWN
Classifier: Development Status :: 4 - Beta
Classifier: Intended Audience :: System Administrators
Classifier: Topic :: System :: Installation/Setup
Classifier: License :: OSI Approved :: MIT License
Classifier: Programming Language :: Python :: 2.7
